LICENSE
MANIFEST.in
README.rst
setup.py
starseqr.py
ssw/__init__.py
ssw/libssw.py
ssw/sswobj.py
ssw/../starseqr_utils/tests/__init__.py
ssw/../starseqr_utils/tests/__init__.pyc
ssw/../starseqr_utils/tests/test_anno.py
ssw/../starseqr_utils/tests/test_anno.pyc
ssw/../starseqr_utils/tests/test_anno_db.py
ssw/../starseqr_utils/tests/test_anno_db.pyc
ssw/../starseqr_utils/tests/test_assembly.py
ssw/../starseqr_utils/tests/test_assembly.pyc
ssw/../starseqr_utils/tests/test_crosshom.py
ssw/../starseqr_utils/tests/test_crosshom.pyc
ssw/../starseqr_utils/tests/test_diversity.py
ssw/../starseqr_utils/tests/test_diversity.pyc
ssw/../starseqr_utils/tests/test_gtf.py
ssw/../starseqr_utils/tests/test_gtf.pyc
ssw/../starseqr_utils/tests/test_homology_graph.py
ssw/../starseqr_utils/tests/test_homology_graph.pyc
ssw/../starseqr_utils/tests/test_primer.py
ssw/../starseqr_utils/tests/test_primer.pyc
ssw/../starseqr_utils/tests/test_readsupport.py
ssw/../starseqr_utils/tests/test_readsupport.pyc
ssw/../starseqr_utils/tests/test_seq.py
ssw/../starseqr_utils/tests/test_seq.pyc
ssw/../starseqr_utils/tests/test_ssw.py
ssw/../starseqr_utils/tests/test_ssw.pyc
ssw/../starseqr_utils/tests/__pycache__/__init__.cpython-34.pyc
ssw/../starseqr_utils/tests/__pycache__/test_anno.cpython-34.pyc
ssw/../starseqr_utils/tests/__pycache__/test_anno_db.cpython-34.pyc
ssw/../starseqr_utils/tests/__pycache__/test_assembly.cpython-34.pyc
ssw/../starseqr_utils/tests/__pycache__/test_crosshom.cpython-34.pyc
ssw/../starseqr_utils/tests/__pycache__/test_diversity.cpython-34.pyc
ssw/../starseqr_utils/tests/__pycache__/test_gtf.cpython-34.pyc
ssw/../starseqr_utils/tests/__pycache__/test_homology_graph.cpython-34.pyc
ssw/../starseqr_utils/tests/__pycache__/test_primer.cpython-34.pyc
ssw/../starseqr_utils/tests/__pycache__/test_readsupport.cpython-34.pyc
ssw/../starseqr_utils/tests/__pycache__/test_seq.cpython-34.pyc
ssw/../starseqr_utils/tests/__pycache__/test_ssw.cpython-34.pyc
starseqr.egg-info/PKG-INFO
starseqr.egg-info/SOURCES.txt
starseqr.egg-info/dependency_links.txt
starseqr.egg-info/not-zip-safe
starseqr.egg-info/requires.txt
starseqr.egg-info/top_level.txt
