Metadata-Version: 1.1
Name: starseqr
Version: 0.6.7
Summary: RNA-Fusion Calling with STAR
Home-page: https://github.com/ExpressionAnalysis/STAR-SEQR
Author: Jeff Jasper
Author-email: jasper1918@gmail.com
License: Custom
Keywords: rna,rna-seq,fusions,chimeric,star
Platform: UNKNOWN
Classifier: Development Status :: 5 - Production/Stable
Classifier: Intended Audience :: Science/Research
Classifier: Natural Language :: English
Classifier: Environment :: Console
Classifier: License :: Other/Proprietary License
Classifier: Operating System :: OS Independent
Classifier: Programming Language :: Python
Classifier: Programming Language :: Python :: 2
Classifier: Programming Language :: Python :: 2.7
Classifier: Programming Language :: Python :: 3
Classifier: Programming Language :: Python :: 3.3
Classifier: Programming Language :: Python :: 3.4
Classifier: Programming Language :: Python :: 3.5
Classifier: Programming Language :: Python :: 3.6
Classifier: Programming Language :: Python :: Implementation :: CPython
Classifier: Intended Audience :: Science/Research
Classifier: Topic :: Scientific/Engineering :: Bio-Informatics
